Metadata-Version: 1.1
Name: malcontent
Version: 0.0.0
Summary: A cross-platform content editor.
Home-page: http://pybee.org/
Author: Russell Keith-Magee
Author-email: russell@keith-magee.com
License: New BSD
Platform: UNKNOWN
Classifier: Development Status :: 3 - Alpha
Classifier: Intended Audience :: Developers
Classifier: License :: OSI Approved :: BSD License
Classifier: Programming Language :: Python :: 3
Classifier: Programming Language :: Python :: 3.4
Classifier: Programming Language :: Python :: 3.5
Classifier: Programming Language :: Python :: 3 :: Only
Classifier: Topic :: Software Development
